blackgeorge/__init__.py
blackgeorge/adapters/__init__.py
blackgeorge/adapters/base.py
blackgeorge/adapters/cost.py
blackgeorge/adapters/instructor_client.py
blackgeorge/adapters/litellm.py
blackgeorge/adapters/litellm_callbacks.py
blackgeorge/async_utils.py
blackgeorge/collaboration/__init__.py
blackgeorge/collaboration/blackboard.py
blackgeorge/collaboration/channel.py
blackgeorge/collaboration/tools.py
blackgeorge/core/__init__.py
blackgeorge/core/event.py
blackgeorge/core/job.py
blackgeorge/core/message.py
blackgeorge/core/pending_action.py
blackgeorge/core/report.py
blackgeorge/core/tool_call.py
blackgeorge/core/types.py
blackgeorge/desk.py
blackgeorge/event_bus.py
blackgeorge/logging.py
blackgeorge/memory/__init__.py
blackgeorge/memory/base.py
blackgeorge/memory/external.py
blackgeorge/memory/in_memory.py
blackgeorge/memory/sqlite.py
blackgeorge/memory/vector.py
blackgeorge/py.typed
blackgeorge/session.py
blackgeorge/store/__init__.py
blackgeorge/store/base.py
blackgeorge/store/in_memory.py
blackgeorge/store/in_memory_session_store.py
blackgeorge/store/session_store.py
blackgeorge/store/sqlite.py
blackgeorge/store/sqlite_session_store.py
blackgeorge/store/state.py
blackgeorge/tools/__init__.py
blackgeorge/tools/base.py
blackgeorge/tools/decorators.py
blackgeorge/tools/execution.py
blackgeorge/tools/mcp.py
blackgeorge/tools/registry.py
blackgeorge/tools/schema.py
blackgeorge/utils.py
blackgeorge/worker.py
blackgeorge/worker_context.py
blackgeorge/worker_messages.py
blackgeorge/worker_runner.py
blackgeorge/worker_tools.py
blackgeorge/workflow/__init__.py
blackgeorge/workflow/context.py
blackgeorge/workflow/flow.py
blackgeorge/workflow/nodes.py
blackgeorge/workflow/result.py
blackgeorge/workforce.py
blackgeorge-1.1.3.dist-info/WHEEL
blackgeorge-1.1.3.dist-info/METADATA
blackgeorge-1.1.3.dist-info/RECORD
