Metadata-Version: 2.3
Name: blackgeorge
Version: 1.1.3
Summary: Agentic framework with desk/worker/workforce primitives
Author: Dušsan Jolović
Author-email: Dušsan Jolović <jolovic@pm.me>
License: MIT License
Requires-Dist: chromadb>=0.4.0
Requires-Dist: instructor[litellm]>=1.11.0
Requires-Dist: litellm>=1.80.0
Requires-Dist: mcp>=1.0.0
Requires-Dist: pydantic>=2.8.0
Requires-Python: >=3.12
Project-URL: Repository, https://github.com/jolovicdev/blackgeorge
